frequency_divider/freq_divider.v

`timescale 1ns/1ps

module freq_divider (
    input  wire clk,
    input  wire rst,
    input  wire [7:0] N,
    output wire clk_out
);
    reg [7:0] count;
    reg pos, neg;

    always @(posedge clk or posedge rst) begin
        if (rst) begin
            count <= 0;
            pos   <= 0;
        end else begin
            count <= (count >= N - 1) ? 0 : count + 1;
            pos   <= (count < N / 2);
        end
    end

    always @(negedge clk or posedge rst) begin
        if (rst) neg <= 0;
        else     neg <= pos;
    end

    assign clk_out = (N == 1)?clk:  (N % 2 == 0)?pos : (pos | neg) ;
endmodule

frequency_divider/testbench_series.v
// testbench_series.v
// One clear example per series
// Base clock = 50 MHz (period = 20ns)
//
// How to run:
//   iverilog -o sim testbench_series.v freq_divider.v
//   vvp sim
//   gtkwave waveform.vcd

`timescale 1ns/1ps

module testbench_series;

    // ─────────────────────────────────────────
    // CLOCK AND RESET
    // period = 20ns = 50 MHz
    // ─────────────────────────────────────────
    reg clk, rst;

    initial clk = 0;
    always #10 clk = ~clk;   // flip every 10ns → 20ns period

    initial begin
        rst = 1;                      // hold reset ON
        repeat(5) @(posedge clk);    // wait 5 clock ticks
        rst = 0;                      // release reset
    end


    // ─────────────────────────────────────────
    // SERIES 1 — 2n  (n=4 → divide by 8)
    //
    //   2n where n=4 → N = 2×4 = 8
    //   Output = 50MHz ÷ 8 = 6.25 MHz
    //   N=8 is even → duty cycle already 50%, no FF trick needed
    // ─────────────────────────────────────────
    wire out_2n;
    freq_divider u_2n (
        .clk     (clk),
        .rst     (rst),
        .N       (8'd8),    // 2×4 = 8
        .clk_out (out_2n)
    );


    // ─────────────────────────────────────────
    // SERIES 2 — 3n  (n=3 → divide by 9)
    //
    //   3n where n=3 → N = 3×3 = 9
    //   Output = 50MHz ÷ 9 = 5.55 MHz
    //   N=9 is ODD → needs −ve edge FF + OR to fix duty cycle
    // ─────────────────────────────────────────
    wire out_3n;
    freq_divider u_3n (
        .clk     (clk),
        .rst     (rst),
        .N       (8'd9),    // 3×3 = 9
        .clk_out (out_3n)
    );


    // ─────────────────────────────────────────
    // SERIES 3 — n²  (n=5 → divide by 25)
    //
    //   n² where n=5 → N = 5×5 = 25
    //   Output = 50MHz ÷ 25 = 2 MHz
    //   N=25 is ODD → needs −ve edge FF + OR to fix duty cycle
    // ─────────────────────────────────────────
    wire out_n2;
    freq_divider u_n2 (
        .clk     (clk),
        .rst     (rst),
        .N       (8'd25),   // 5² = 25
        .clk_out (out_n2)
    );


    // ─────────────────────────────────────────
    // SERIES 4 — 2^n  (n=4 → divide by 16)
    //
    //   2^n where n=4 → N = 2⁴ = 16
    //   Output = 50MHz ÷ 16 = 3.125 MHz
    //   N=16 is even AND a power of 2 → easiest case, free 50% DC
    // ─────────────────────────────────────────
    wire out_2pn;
    freq_divider u_2pn (
        .clk     (clk),
        .rst     (rst),
        .N       (8'd16),   // 2⁴ = 16
        .clk_out (out_2pn)
    );


    // ─────────────────────────────────────────
    // RECORD AND RUN
    // ─────────────────────────────────────────
    initial begin
        $dumpfile("waveform.vcd");
        $dumpvars(0, testbench_series);

        // run long enough to see several cycles of the
        // slowest signal (÷25 → period = 500ns)
        // so run for at least 10 × 500ns = 5000ns
        #5000;

        $display("Done. Signals to look at in GTKWave:");
        $display("  clk     = 50 MHz base clock");
        $display("  out_2n  = 6.25 MHz  (50MHz / 8,  series 2n, n=4)");
        $display("  out_3n  = 5.55 MHz  (50MHz / 9,  series 3n, n=3)");
        $display("  out_n2  = 2.00 MHz  (50MHz / 25, series n2, n=5)");
        $display("  out_2pn = 3.125 MHz (50MHz / 16, series 2^n, n=4)");

        $finish;
    end

endmodule

frequency_divider/waveform.vcd
$date
	Wed Mar 11 11:07:54 2026
$end
$version
	Icarus Verilog
$end
$timescale
	1ps
$end
$scope module testbench_series $end
$var wire 1 ! out_n2 $end
$var wire 1 " out_3n $end
$var wire 1 # out_2pn $end
$var wire 1 $ out_2n $end
$var reg 1 % clk $end
$var reg 1 & rst $end
$scope module u_2n $end
$var wire 8 ' N [7:0] $end
$var wire 1 % clk $end
$var wire 1 & rst $end
$var wire 1 $ clk_out $end
$var reg 8 ( count [7:0] $end
$var reg 1 ) neg $end
$var reg 1 * pos $end
$upscope $end
$scope module u_2pn $end
$var wire 8 + N [7:0] $end
$var wire 1 % clk $end
$var wire 1 & rst $end
$var wire 1 # clk_out $end
$var reg 8 , count [7:0] $end
$var reg 1 - neg $end
$var reg 1 . pos $end
$upscope $end
$scope module u_3n $end
$var wire 8 / N [7:0] $end
$var wire 1 % clk $end
$var wire 1 & rst $end
$var wire 1 " clk_out $end
$var reg 8 0 count [7:0] $end
$var reg 1 1 neg $end
$var reg 1 2 pos $end
$upscope $end
$scope module u_n2 $end
$var wire 8 3 N [7:0] $end
$var wire 1 % clk $end
$var wire 1 & rst $end
$var wire 1 ! clk_out $end
$var reg 8 4 count [7:0] $end
$var reg 1 5 neg $end
$var reg 1 6 pos $end
$upscope $end
$upscope $end
$enddefinitions $end
$comment Show the parameter values. $end
$dumpall
$end
#0
$dumpvars
06
05
b0 4
b11001 3
02
01
b0 0
b1001 /
0.
0-
b0 ,
b10000 +
0*
0)
b0 (
b1000 '
1&
0%
0$
0#
0"
0!
$end
#10000
1%
#20000
0%
#30000
1%
#40000
0%
#50000
1%
#60000
0%
#70000
1%
#80000
0%
#90000
1!
1"
1#
1$
1.
b1 ,
16
b1 4
12
b1 0
1*
b1 (
0&
1%
#100000
1-
15
11
1)
0%
#110000
b10 (
b10 0
b10 4
b10 ,
1%
#120000
0%
#130000
b11 ,
b11 4
b11 0
b11 (
1%
#140000
0%
#150000
b100 (
b100 0
b100 4
b100 ,
1%
#160000
0%
#170000
0$
b101 ,
b101 4
02
b101 0
0*
b101 (
1%
#180000
0"
01
0)
0%
#190000
b110 (
b110 0
b110 4
b110 ,
1%
#200000
0%
#210000
b111 ,
b111 4
b111 0
b111 (
1%
#220000
0%
#230000
b0 (
b1000 0
b1000 4
b1000 ,
1%
#240000
0%
#250000
0#
1$
0.
b1001 ,
b1001 4
b0 0
1*
b1 (
1%
#260000
0-
1)
0%
#270000
1"
b10 (
12
b1 0
b1010 4
b1010 ,
1%
#280000
11
0%
#290000
b1011 ,
b1011 4
b10 0
b11 (
1%
#300000
0%
#310000
b100 (
b11 0
b1100 4
b1100 ,
1%
#320000
0%
#330000
0$
b1101 ,
06
b1101 4
b100 0
0*
b101 (
1%
#340000
0!
05
0)
0%
#350000
b110 (
02
b101 0
b1110 4
b1110 ,
1%
#360000
0"
01
0%
#370000
b1111 ,
b1111 4
b110 0
b111 (
1%
#380000
0%
#390000
b0 (
b111 0
b10000 4
b0 ,
1%
#400000
0%
#410000
1#
1$
1.
b1 ,
b10001 4
b1000 0
1*
b1 (
1%
#420000
1-
1)
0%
#430000
b10 (
b0 0
b10010 4
b10 ,
1%
#440000
0%
#450000
1"
b11 ,
b10011 4
12
b1 0
b11 (
1%
#460000
11
0%
#470000
b100 (
b10 0
b10100 4
b100 ,
1%
#480000
0%
#490000
0$
b101 ,
b10101 4
b11 0
0*
b101 (
1%
#500000
0)
0%
#510000
b110 (
b100 0
b10110 4
b110 ,
1%
#520000
0%
#530000
b111 ,
b10111 4
02
b101 0
b111 (
1%
#540000
0"
01
0%
#550000
b0 (
b110 0
b11000 4
b1000 ,
1%
#560000
0%
#570000
0#
1$
0.
b1001 ,
b0 4
b111 0
1*
b1 (
1%
#580000
0-
1)
0%
#590000
1!
b10 (
b1000 0
16
b1 4
b1010 ,
1%
#600000
15
0%
#610000
b1011 ,
b10 4
b0 0
b11 (
1%
#620000
0%
#630000
1"
b100 (
12
b1 0
b11 4
b1100 ,
1%
#640000
11
0%
#650000
0$
b1101 ,
b100 4
b10 0
0*
b101 (
1%
#660000
0)
0%
#670000
b110 (
b11 0
b101 4
b1110 ,
1%
#680000
0%
#690000
b1111 ,
b110 4
b100 0
b111 (
1%
#700000
0%
#710000
b0 (
02
b101 0
b111 4
b0 ,
1%
#720000
0"
01
0%
#730000
1#
1$
1.
b1 ,
b1000 4
b110 0
1*
b1 (
1%
#740000
1-
1)
0%
#750000
b10 (
b111 0
b1001 4
b10 ,
1%
#760000
0%
#770000
b11 ,
b1010 4
b1000 0
b11 (
1%
#780000
0%
#790000
b100 (
b0 0
b1011 4
b100 ,
1%
#800000
0%
#810000
1"
0$
b101 ,
b1100 4
12
b1 0
0*
b101 (
1%
#820000
11
0)
0%
#830000
b110 (
b10 0
06
b1101 4
b110 ,
1%
#840000
0!
05
0%
#850000
b111 ,
b1110 4
b11 0
b111 (
1%
#860000
0%
#870000
b0 (
b100 0
b1111 4
b1000 ,
1%
#880000
0%
#890000
0#
1$
0.
b1001 ,
b10000 4
02
b101 0
1*
b1 (
1%
#900000
0"
0-
01
1)
0%
#910000
b10 (
b110 0
b10001 4
b1010 ,
1%
#920000
0%
#930000
b1011 ,
b10010 4
b111 0
b11 (
1%
#940000
0%
#950000
b100 (
b1000 0
b10011 4
b1100 ,
1%
#960000
0%
#970000
0$
b1101 ,
b10100 4
b0 0
0*
b101 (
1%
#980000
0)
0%
#990000
1"
b110 (
12
b1 0
b10101 4
b1110 ,
1%
#1000000
11
0%
#1010000
b1111 ,
b10110 4
b10 0
b111 (
1%
#1020000
0%
#1030000
b0 (
b11 0
b10111 4
b0 ,
1%
#1040000
0%
#1050000
1#
1$
1.
b1 ,
b11000 4
b100 0
1*
b1 (
1%
#1060000
1-
1)
0%
#1070000
b10 (
02
b101 0
b0 4
b10 ,
1%
#1080000
0"
01
0%
#1090000
1!
b11 ,
16
b1 4
b110 0
b11 (
1%
#1100000
15
0%
#1110000
b100 (
b111 0
b10 4
b100 ,
1%
#1120000
0%
#1130000
0$
b101 ,
b11 4
b1000 0
0*
b101 (
1%
#1140000
0)
0%
#1150000
b110 (
b0 0
b100 4
b110 ,
1%
#1160000
0%
#1170000
1"
b111 ,
b101 4
12
b1 0
b111 (
1%
#1180000
11
0%
#1190000
b0 (
b10 0
b110 4
b1000 ,
1%
#1200000
0%
#1210000
0#
1$
0.
b1001 ,
b111 4
b11 0
1*
b1 (
1%
#1220000
0-
1)
0%
#1230000
b10 (
b100 0
b1000 4
b1010 ,
1%
#1240000
0%
#1250000
b1011 ,
b1001 4
02
b101 0
b11 (
1%
#1260000
0"
01
0%
#1270000
b100 (
b110 0
b1010 4
b1100 ,
1%
#1280000
0%
#1290000
0$
b1101 ,
b1011 4
b111 0
0*
b101 (
1%
#1300000
0)
0%
#1310000
b110 (
b1000 0
b1100 4
b1110 ,
1%
#1320000
0%
#1330000
b1111 ,
06
b1101 4
b0 0
b111 (
1%
#1340000
0!
05
0%
#1350000
1"
b0 (
12
b1 0
b1110 4
b0 ,
1%
#1360000
11
0%
#1370000
1#
1$
1.
b1 ,
b1111 4
b10 0
1*
b1 (
1%
#1380000
1-
1)
0%
#1390000
b10 (
b11 0
b10000 4
b10 ,
1%
#1400000
0%
#1410000
b11 ,
b10001 4
b100 0
b11 (
1%
#1420000
0%
#1430000
b100 (
02
b101 0
b10010 4
b100 ,
1%
#1440000
0"
01
0%
#1450000
0$
b101 ,
b10011 4
b110 0
0*
b101 (
1%
#1460000
0)
0%
#1470000
b110 (
b111 0
b10100 4
b110 ,
1%
#1480000
0%
#1490000
b111 ,
b10101 4
b1000 0
b111 (
1%
#1500000
0%
#1510000
b0 (
b0 0
b10110 4
b1000 ,
1%
#1520000
0%
#1530000
1"
0#
1$
0.
b1001 ,
b10111 4
12
b1 0
1*
b1 (
1%
#1540000
0-
11
1)
0%
#1550000
b10 (
b10 0
b11000 4
b1010 ,
1%
#1560000
0%
#1570000
b1011 ,
b0 4
b11 0
b11 (
1%
#1580000
0%
#1590000
1!
b100 (
b100 0
16
b1 4
b1100 ,
1%
#1600000
15
0%
#1610000
0$
b1101 ,
b10 4
02
b101 0
0*
b101 (
1%
#1620000
0"
01
0)
0%
#1630000
b110 (
b110 0
b11 4
b1110 ,
1%
#1640000
0%
#1650000
b1111 ,
b100 4
b111 0
b111 (
1%
#1660000
0%
#1670000
b0 (
b1000 0
b101 4
b0 ,
1%
#1680000
0%
#1690000
1#
1$
1.
b1 ,
b110 4
b0 0
1*
b1 (
1%
#1700000
1-
1)
0%
#1710000
1"
b10 (
12
b1 0
b111 4
b10 ,
1%
#1720000
11
0%
#1730000
b11 ,
b1000 4
b10 0
b11 (
1%
#1740000
0%
#1750000
b100 (
b11 0
b1001 4
b100 ,
1%
#1760000
0%
#1770000
0$
b101 ,
b1010 4
b100 0
0*
b101 (
1%
#1780000
0)
0%
#1790000
b110 (
02
b101 0
b1011 4
b110 ,
1%
#1800000
0"
01
0%
#1810000
b111 ,
b1100 4
b110 0
b111 (
1%
#1820000
0%
#1830000
b0 (
b111 0
06
b1101 4
b1000 ,
1%
#1840000
0!
05
0%
#1850000
0#
1$
0.
b1001 ,
b1110 4
b1000 0
1*
b1 (
1%
#1860000
0-
1)
0%
#1870000
b10 (
b0 0
b1111 4
b1010 ,
1%
#1880000
0%
#1890000
1"
b1011 ,
b10000 4
12
b1 0
b11 (
1%
#1900000
11
0%
#1910000
b100 (
b10 0
b10001 4
b1100 ,
1%
#1920000
0%
#1930000
0$
b1101 ,
b10010 4
b11 0
0*
b101 (
1%
#1940000
0)
0%
#1950000
b110 (
b100 0
b10011 4
b1110 ,
1%
#1960000
0%
#1970000
b1111 ,
b10100 4
02
b101 0
b111 (
1%
#1980000
0"
01
0%
#1990000
b0 (
b110 0
b10101 4
b0 ,
1%
#2000000
0%
#2010000
1#
1$
1.
b1 ,
b10110 4
b111 0
1*
b1 (
1%
#2020000
1-
1)
0%
#2030000
b10 (
b1000 0
b10111 4
b10 ,
1%
#2040000
0%
#2050000
b11 ,
b11000 4
b0 0
b11 (
1%
#2060000
0%
#2070000
1"
b100 (
12
b1 0
b0 4
b100 ,
1%
#2080000
11
0%
#2090000
1!
0$
b101 ,
16
b1 4
b10 0
0*
b101 (
1%
#2100000
15
0)
0%
#2110000
b110 (
b11 0
b10 4
b110 ,
1%
#2120000
0%
#2130000
b111 ,
b11 4
b100 0
b111 (
1%
#2140000
0%
#2150000
b0 (
02
b101 0
b100 4
b1000 ,
1%
#2160000
0"
01
0%
#2170000
0#
1$
0.
b1001 ,
b101 4
b110 0
1*
b1 (
1%
#2180000
0-
1)
0%
#2190000
b10 (
b111 0
b110 4
b1010 ,
1%
#2200000
0%
#2210000
b1011 ,
b111 4
b1000 0
b11 (
1%
#2220000
0%
#2230000
b100 (
b0 0
b1000 4
b1100 ,
1%
#2240000
0%
#2250000
1"
0$
b1101 ,
b1001 4
12
b1 0
0*
b101 (
1%
#2260000
11
0)
0%
#2270000
b110 (
b10 0
b1010 4
b1110 ,
1%
#2280000
0%
#2290000
b1111 ,
b1011 4
b11 0
b111 (
1%
#2300000
0%
#2310000
b0 (
b100 0
b1100 4
b0 ,
1%
#2320000
0%
#2330000
1#
1$
1.
b1 ,
06
b1101 4
02
b101 0
1*
b1 (
1%
#2340000
0!
0"
1-
05
01
1)
0%
#2350000
b10 (
b110 0
b1110 4
b10 ,
1%
#2360000
0%
#2370000
b11 ,
b1111 4
b111 0
b11 (
1%
#2380000
0%
#2390000
b100 (
b1000 0
b10000 4
b100 ,
1%
#2400000
0%
#2410000
0$
b101 ,
b10001 4
b0 0
0*
b101 (
1%
#2420000
0)
0%
#2430000
1"
b110 (
12
b1 0
b10010 4
b110 ,
1%
#2440000
11
0%
#2450000
b111 ,
b10011 4
b10 0
b111 (
1%
#2460000
0%
#2470000
b0 (
b11 0
b10100 4
b1000 ,
1%
#2480000
0%
#2490000
0#
1$
0.
b1001 ,
b10101 4
b100 0
1*
b1 (
1%
#2500000
0-
1)
0%
#2510000
b10 (
02
b101 0
b10110 4
b1010 ,
1%
#2520000
0"
01
0%
#2530000
b1011 ,
b10111 4
b110 0
b11 (
1%
#2540000
0%
#2550000
b100 (
b111 0
b11000 4
b1100 ,
1%
#2560000
0%
#2570000
0$
b1101 ,
b0 4
b1000 0
0*
b101 (
1%
#2580000
0)
0%
#2590000
1!
b110 (
b0 0
16
b1 4
b1110 ,
1%
#2600000
15
0%
#2610000
1"
b1111 ,
b10 4
12
b1 0
b111 (
1%
#2620000
11
0%
#2630000
b0 (
b10 0
b11 4
b0 ,
1%
#2640000
0%
#2650000
1#
1$
1.
b1 ,
b100 4
b11 0
1*
b1 (
1%
#2660000
1-
1)
0%
#2670000
b10 (
b100 0
b101 4
b10 ,
1%
#2680000
0%
#2690000
b11 ,
b110 4
02
b101 0
b11 (
1%
#2700000
0"
01
0%
#2710000
b100 (
b110 0
b111 4
b100 ,
1%
#2720000
0%
#2730000
0$
b101 ,
b1000 4
b111 0
0*
b101 (
1%
#2740000
0)
0%
#2750000
b110 (
b1000 0
b1001 4
b110 ,
1%
#2760000
0%
#2770000
b111 ,
b1010 4
b0 0
b111 (
1%
#2780000
0%
#2790000
1"
b0 (
12
b1 0
b1011 4
b1000 ,
1%
#2800000
11
0%
#2810000
0#
1$
0.
b1001 ,
b1100 4
b10 0
1*
b1 (
1%
#2820000
0-
1)
0%
#2830000
b10 (
b11 0
06
b1101 4
b1010 ,
1%
#2840000
0!
05
0%
#2850000
b1011 ,
b1110 4
b100 0
b11 (
1%
#2860000
0%
#2870000
b100 (
02
b101 0
b1111 4
b1100 ,
1%
#2880000
0"
01
0%
#2890000
0$
b1101 ,
b10000 4
b110 0
0*
b101 (
1%
#2900000
0)
0%
#2910000
b110 (
b111 0
b10001 4
b1110 ,
1%
#2920000
0%
#2930000
b1111 ,
b10010 4
b1000 0
b111 (
1%
#2940000
0%
#2950000
b0 (
b0 0
b10011 4
b0 ,
1%
#2960000
0%
#2970000
1"
1#
1$
1.
b1 ,
b10100 4
12
b1 0
1*
b1 (
1%
#2980000
1-
11
1)
0%
#2990000
b10 (
b10 0
b10101 4
b10 ,
1%
#3000000
0%
#3010000
b11 ,
b10110 4
b11 0
b11 (
1%
#3020000
0%
#3030000
b100 (
b100 0
b10111 4
b100 ,
1%
#3040000
0%
#3050000
0$
b101 ,
b11000 4
02
b101 0
0*
b101 (
1%
#3060000
0"
01
0)
0%
#3070000
b110 (
b110 0
b0 4
b110 ,
1%
#3080000
0%
#3090000
1!
b111 ,
16
b1 4
b111 0
b111 (
1%
#3100000
15
0%
#3110000
b0 (
b1000 0
b10 4
b1000 ,
1%
#3120000
0%
#3130000
0#
1$
0.
b1001 ,
b11 4
b0 0
1*
b1 (
1%
#3140000
0-
1)
0%
#3150000
1"
b10 (
12
b1 0
b100 4
b1010 ,
1%
#3160000
11
0%
#3170000
b1011 ,
b101 4
b10 0
b11 (
1%
#3180000
0%
#3190000
b100 (
b11 0
b110 4
b1100 ,
1%
#3200000
0%
#3210000
0$
b1101 ,
b111 4
b100 0
0*
b101 (
1%
#3220000
0)
0%
#3230000
b110 (
02
b101 0
b1000 4
b1110 ,
1%
#3240000
0"
01
0%
#3250000
b1111 ,
b1001 4
b110 0
b111 (
1%
#3260000
0%
#3270000
b0 (
b111 0
b1010 4
b0 ,
1%
#3280000
0%
#3290000
1#
1$
1.
b1 ,
b1011 4
b1000 0
1*
b1 (
1%
#3300000
1-
1)
0%
#3310000
b10 (
b0 0
b1100 4
b10 ,
1%
#3320000
0%
#3330000
1"
b11 ,
06
b1101 4
12
b1 0
b11 (
1%
#3340000
0!
05
11
0%
#3350000
b100 (
b10 0
b1110 4
b100 ,
1%
#3360000
0%
#3370000
0$
b101 ,
b1111 4
b11 0
0*
b101 (
1%
#3380000
0)
0%
#3390000
b110 (
b100 0
b10000 4
b110 ,
1%
#3400000
0%
#3410000
b111 ,
b10001 4
02
b101 0
b111 (
1%
#3420000
0"
01
0%
#3430000
b0 (
b110 0
b10010 4
b1000 ,
1%
#3440000
0%
#3450000
0#
1$
0.
b1001 ,
b10011 4
b111 0
1*
b1 (
1%
#3460000
0-
1)
0%
#3470000
b10 (
b1000 0
b10100 4
b1010 ,
1%
#3480000
0%
#3490000
b1011 ,
b10101 4
b0 0
b11 (
1%
#3500000
0%
#3510000
1"
b100 (
12
b1 0
b10110 4
b1100 ,
1%
#3520000
11
0%
#3530000
0$
b1101 ,
b10111 4
b10 0
0*
b101 (
1%
#3540000
0)
0%
#3550000
b110 (
b11 0
b11000 4
b1110 ,
1%
#3560000
0%
#3570000
b1111 ,
b0 4
b100 0
b111 (
1%
#3580000
0%
#3590000
1!
b0 (
02
b101 0
16
b1 4
b0 ,
1%
#3600000
0"
01
15
0%
#3610000
1#
1$
1.
b1 ,
b10 4
b110 0
1*
b1 (
1%
#3620000
1-
1)
0%
#3630000
b10 (
b111 0
b11 4
b10 ,
1%
#3640000
0%
#3650000
b11 ,
b100 4
b1000 0
b11 (
1%
#3660000
0%
#3670000
b100 (
b0 0
b101 4
b100 ,
1%
#3680000
0%
#3690000
1"
0$
b101 ,
b110 4
12
b1 0
0*
b101 (
1%
#3700000
11
0)
0%
#3710000
b110 (
b10 0
b111 4
b110 ,
1%
#3720000
0%
#3730000
b111 ,
b1000 4
b11 0
b111 (
1%
#3740000
0%
#3750000
b0 (
b100 0
b1001 4
b1000 ,
1%
#3760000
0%
#3770000
0#
1$
0.
b1001 ,
b1010 4
02
b101 0
1*
b1 (
1%
#3780000
0"
0-
01
1)
0%
#3790000
b10 (
b110 0
b1011 4
b1010 ,
1%
#3800000
0%
#3810000
b1011 ,
b1100 4
b111 0
b11 (
1%
#3820000
0%
#3830000
b100 (
b1000 0
06
b1101 4
b1100 ,
1%
#3840000
0!
05
0%
#3850000
0$
b1101 ,
b1110 4
b0 0
0*
b101 (
1%
#3860000
0)
0%
#3870000
1"
b110 (
12
b1 0
b1111 4
b1110 ,
1%
#3880000
11
0%
#3890000
b1111 ,
b10000 4
b10 0
b111 (
1%
#3900000
0%
#3910000
b0 (
b11 0
b10001 4
b0 ,
1%
#3920000
0%
#3930000
1#
1$
1.
b1 ,
b10010 4
b100 0
1*
b1 (
1%
#3940000
1-
1)
0%
#3950000
b10 (
02
b101 0
b10011 4
b10 ,
1%
#3960000
0"
01
0%
#3970000
b11 ,
b10100 4
b110 0
b11 (
1%
#3980000
0%
#3990000
b100 (
b111 0
b10101 4
b100 ,
1%
#4000000
0%
#4010000
0$
b101 ,
b10110 4
b1000 0
0*
b101 (
1%
#4020000
0)
0%
#4030000
b110 (
b0 0
b10111 4
b110 ,
1%
#4040000
0%
#4050000
1"
b111 ,
b11000 4
12
b1 0
b111 (
1%
#4060000
11
0%
#4070000
b0 (
b10 0
b0 4
b1000 ,
1%
#4080000
0%
#4090000
1!
0#
1$
0.
b1001 ,
16
b1 4
b11 0
1*
b1 (
1%
#4100000
0-
15
1)
0%
#4110000
b10 (
b100 0
b10 4
b1010 ,
1%
#4120000
0%
#4130000
b1011 ,
b11 4
02
b101 0
b11 (
1%
#4140000
0"
01
0%
#4150000
b100 (
b110 0
b100 4
b1100 ,
1%
#4160000
0%
#4170000
0$
b1101 ,
b101 4
b111 0
0*
b101 (
1%
#4180000
0)
0%
#4190000
b110 (
b1000 0
b110 4
b1110 ,
1%
#4200000
0%
#4210000
b1111 ,
b111 4
b0 0
b111 (
1%
#4220000
0%
#4230000
1"
b0 (
12
b1 0
b1000 4
b0 ,
1%
#4240000
11
0%
#4250000
1#
1$
1.
b1 ,
b1001 4
b10 0
1*
b1 (
1%
#4260000
1-
1)
0%
#4270000
b10 (
b11 0
b1010 4
b10 ,
1%
#4280000
0%
#4290000
b11 ,
b1011 4
b100 0
b11 (
1%
#4300000
0%
#4310000
b100 (
02
b101 0
b1100 4
b100 ,
1%
#4320000
0"
01
0%
#4330000
0$
b101 ,
06
b1101 4
b110 0
0*
b101 (
1%
#4340000
0!
05
0)
0%
#4350000
b110 (
b111 0
b1110 4
b110 ,
1%
#4360000
0%
#4370000
b111 ,
b1111 4
b1000 0
b111 (
1%
#4380000
0%
#4390000
b0 (
b0 0
b10000 4
b1000 ,
1%
#4400000
0%
#4410000
1"
0#
1$
0.
b1001 ,
b10001 4
12
b1 0
1*
b1 (
1%
#4420000
0-
11
1)
0%
#4430000
b10 (
b10 0
b10010 4
b1010 ,
1%
#4440000
0%
#4450000
b1011 ,
b10011 4
b11 0
b11 (
1%
#4460000
0%
#4470000
b100 (
b100 0
b10100 4
b1100 ,
1%
#4480000
0%
#4490000
0$
b1101 ,
b10101 4
02
b101 0
0*
b101 (
1%
#4500000
0"
01
0)
0%
#4510000
b110 (
b110 0
b10110 4
b1110 ,
1%
#4520000
0%
#4530000
b1111 ,
b10111 4
b111 0
b111 (
1%
#4540000
0%
#4550000
b0 (
b1000 0
b11000 4
b0 ,
1%
#4560000
0%
#4570000
1#
1$
1.
b1 ,
b0 4
b0 0
1*
b1 (
1%
#4580000
1-
1)
0%
#4590000
1"
1!
b10 (
12
b1 0
16
b1 4
b10 ,
1%
#4600000
11
15
0%
#4610000
b11 ,
b10 4
b10 0
b11 (
1%
#4620000
0%
#4630000
b100 (
b11 0
b11 4
b100 ,
1%
#4640000
0%
#4650000
0$
b101 ,
b100 4
b100 0
0*
b101 (
1%
#4660000
0)
0%
#4670000
b110 (
02
b101 0
b101 4
b110 ,
1%
#4680000
0"
01
0%
#4690000
b111 ,
b110 4
b110 0
b111 (
1%
#4700000
0%
#4710000
b0 (
b111 0
b111 4
b1000 ,
1%
#4720000
0%
#4730000
0#
1$
0.
b1001 ,
b1000 4
b1000 0
1*
b1 (
1%
#4740000
0-
1)
0%
#4750000
b10 (
b0 0
b1001 4
b1010 ,
1%
#4760000
0%
#4770000
1"
b1011 ,
b1010 4
12
b1 0
b11 (
1%
#4780000
11
0%
#4790000
b100 (
b10 0
b1011 4
b1100 ,
1%
#4800000
0%
#4810000
0$
b1101 ,
b1100 4
b11 0
0*
b101 (
1%
#4820000
0)
0%
#4830000
b110 (
b100 0
06
b1101 4
b1110 ,
1%
#4840000
0!
05
0%
#4850000
b1111 ,
b1110 4
02
b101 0
b111 (
1%
#4860000
0"
01
0%
#4870000
b0 (
b110 0
b1111 4
b0 ,
1%
#4880000
0%
#4890000
1#
1$
1.
b1 ,
b10000 4
b111 0
1*
b1 (
1%
#4900000
1-
1)
0%
#4910000
b10 (
b1000 0
b10001 4
b10 ,
1%
#4920000
0%
#4930000
b11 ,
b10010 4
b0 0
b11 (
1%
#4940000
0%
#4950000
1"
b100 (
12
b1 0
b10011 4
b100 ,
1%
#4960000
11
0%
#4970000
0$
b101 ,
b10100 4
b10 0
0*
b101 (
1%
#4980000
0)
0%
#4990000
b110 (
b11 0
b10101 4
b110 ,
1%
